thefoxUtils/__init__.py
thefoxUtils/charset.py
thefoxUtils/composites.py
thefoxUtils/ftml2txt.py
thefoxUtils/glyphdata.py
thefoxUtils/linespacing.py
thefoxUtils/tf.py
thefoxUtils/unidata.py
thefoxUtils/unidump.py
thefoxUtils/unikey.py
thefoxutils-25.4.0.dist-info/entry_points.txt
thefoxutils-25.4.0.dist-info/licenses/LICENSE
thefoxutils-25.4.0.dist-info/WHEEL
thefoxutils-25.4.0.dist-info/METADATA
thefoxutils-25.4.0.dist-info/RECORD
