Metadata-Version: 2.4
Name: thefoxUtils
Version: 25.4.0
Summary: Unicode utilities
Author-email: Bobby de Vos <bobby_devos@sil.org>
Requires-Python: >= 3.9
Classifier: Programming Language :: Python :: 3
Classifier: License :: OSI Approved :: MIT License
Classifier: Operating System :: OS Independent
License-File: LICENSE
Requires-Dist: fontParts
Requires-Dist: uharfbuzz
Requires-Dist: cssutils
Project-URL: Bug Tracker, https://github.com/devosb/thefoxutils/issues
Project-URL: Homepage, https://github.com/devosb/thefoxutils/README.md
Project-URL: Repository, https://github.com/devosb/thefoxutils
